badtooth/__init__.py
badtooth/debug_constants.py
badtooth/entropy.py
badtooth/kernel32.py
badtooth/kernel32_structs.py
badtooth/memory.py
badtooth/ntdll.py
badtooth/ntdll_structs.py
badtooth/winerror_constants.py
badtooth/winnt_constants.py
badtooth/x86.py
badtooth-0.0.1.dist-info/LICENSE
badtooth-0.0.1.dist-info/METADATA
badtooth-0.0.1.dist-info/WHEEL
badtooth-0.0.1.dist-info/top_level.txt
badtooth-0.0.1.dist-info/RECORD
