Metadata-Version: 2.1
Name: badtooth
Version: 0.0.1
Summary: A memory hacking package for windows games.
Home-page: https://github.com/samsonpianofingers/BadTooth
Author: Samson PianoFingers
Author-email: itsthatguyagain3@gmail.com
License: UNKNOWN
Platform: UNKNOWN
Classifier: Development Status :: 3 - Alpha
Classifier: Programming Language :: Python :: 3.6
Classifier: Intended Audience :: Other Audience
Classifier: Topic :: Games/Entertainment
Classifier: License :: OSI Approved :: MIT License
Classifier: Operating System :: Microsoft :: Windows :: Windows 10
Requires-Python: >=3.6
Requires-Dist: capstone
Requires-Dist: keystone-engine
Requires-Dist: pefile
